README.md
setup.py
easyquant/__init__.py
easyquant/base.py
easyquant/config.py
easyquant/const.py
easyquant/exceptions.py
easyquant/indicators.py
easyquant/logger.py
easyquant/market.py
easyquant/position.py
easyquant/push.py
easyquant/storage.py
easyquant/time.py
easyquant.egg-info/PKG-INFO
easyquant.egg-info/SOURCES.txt
easyquant.egg-info/dependency_links.txt
easyquant.egg-info/requires.txt
easyquant.egg-info/top_level.txt
easyquant/exchange/__init__.py
easyquant/exchange/binance/__init__.py
easyquant/exchange/binance/binance_spot.py
easyquant/exchange/huobi/__init__.py
easyquant/exchange/huobi/huobi_spot.py
easyquant/exchange/huobi/util.py
easyquant/exchange/okex/__init__.py
easyquant/exchange/okex/account_api.py
easyquant/exchange/okex/client.py
easyquant/exchange/okex/consts.py
easyquant/exchange/okex/exceptions.py
easyquant/exchange/okex/futures_api.py
easyquant/exchange/okex/index_api.py
easyquant/exchange/okex/information_api.py
easyquant/exchange/okex/lever_api.py
easyquant/exchange/okex/option_api.py
easyquant/exchange/okex/spot_api.py
easyquant/exchange/okex/swap_api.py
easyquant/exchange/okex/system_api.py
easyquant/exchange/okex/utils.py
easyquant/exchange/util/__init__.py
easyquant/exchange/util/requests.py
easyquant/trade/__init__.py
easyquant/trade/binancespot.py
easyquant/trade/huobispot.py
easyquant/trade/okexspot.py