Metadata-Version: 1.0
Name: easyquant
Version: 0.0.9
Summary: Professional quant framework
Home-page: https://github.com/Gary-Hertel/easyquant
Author: Gary-Hertel
Author-email: easyquant@foxmail.com
License: MIT
Keywords: easyquant,quant,framework,btc,trade
Platform: any
